cibercca/__init__.py
cibercca/__main__.py
cibercca/c_alive.py
cibercca/c_alive_command.py
cibercca/c_database.py
cibercca/c_interfaces.py
cibercca/c_interfaces_command.py
cibercca/c_interfaces_excel.py
cibercca/c_inventory_command.py
cibercca/c_login.py
cibercca/c_login_command.py
cibercca/c_merge_ping.py
cibercca/c_merge_ping_command.py
cibercca/c_nornir.py
cibercca/c_ping_command.py
cibercca/c_ping_dst.py
cibercca/c_ping_dst_excel.py
cibercca/c_ping_src.py
cibercca/c_ping_src_excel.py
cibercca/c_records.py
cibercca/c_records_command.py
cibercca/c_templates.py
cibercca/c_typer.py
cibercca/c_typer_callback.py
cibercca/data_cibercca.py
cibercca/database.py
cibercca/inventory/.gitignore
cibercca/inventory/dbconnect.yaml
cibercca/inventory/defaults.yaml
cibercca/inventory/groups.yaml
cibercca/inventory/hosts.yaml
cibercca/main.py
cibercca-0.2.6.dist-info/LICENSE
cibercca-0.2.6.dist-info/METADATA
cibercca-0.2.6.dist-info/WHEEL
cibercca-0.2.6.dist-info/entry_points.txt
cibercca-0.2.6.dist-info/RECORD
