Metadata-Version: 2.1
Name: cibercca
Version: 0.2.6
Summary: CiberC Code Automation - reports excel and json formats and save data in MongoDB
License: BSD 3-Clause License
Author: Verni Hernandez
Author-email: verni.hernandez@ciberc.com
Requires-Python: >=3.8,<4.0
Classifier: Environment :: Console
Classifier: Intended Audience :: Developers
Classifier: Intended Audience :: Education
Classifier: Intended Audience :: End Users/Desktop
Classifier: Intended Audience :: Information Technology
Classifier: Intended Audience :: System Administrators
Classifier: License :: Other/Proprietary License
Classifier: Operating System :: OS Independent
Classifier: Programming Language :: Python
Classifier: Programming Language :: Python :: 3
Classifier: Programming Language :: Python :: 3.8
Classifier: Programming Language :: Python :: 3.9
Classifier: Programming Language :: Python :: 3.10
Classifier: Programming Language :: Python :: 3.11
Classifier: Programming Language :: Python :: 3.12
Classifier: Programming Language :: Python :: 3 :: Only
Classifier: Topic :: Software Development
Classifier: Topic :: Software Development :: Libraries
Classifier: Topic :: Software Development :: Libraries :: Application Frameworks
Classifier: Topic :: Software Development :: Libraries :: Python Modules
Classifier: Topic :: Terminals
Classifier: Topic :: Utilities
Classifier: Typing :: Typed
Requires-Dist: Deprecated (==1.2.14)
Requires-Dist: Flask (==3.0.3)
Requires-Dist: Jinja2 (==3.1.4)
Requires-Dist: MarkupSafe (==2.1.5)
Requires-Dist: PyNaCl (==1.5.0)
Requires-Dist: PyYAML (==6.0)
Requires-Dist: Werkzeug (==3.0.3)
Requires-Dist: bcrypt (==4.1.3)
Requires-Dist: blinker (==1.8.2)
Requires-Dist: certifi (==2024.6.2)
Requires-Dist: cffi (==1.16.0)
Requires-Dist: charset-normalizer (==3.3.2)
Requires-Dist: ciscoconfparse (==1.9.41)
Requires-Dist: click (==8.1.7)
Requires-Dist: colorama (==0.4.6)
Requires-Dist: cryptography (==42.0.8)
Requires-Dist: dnspython (==2.6.1)
Requires-Dist: et-xmlfile (==1.1.0)
Requires-Dist: future (==1.0.0)
Requires-Dist: hier-config (==2.2.3)
Requires-Dist: hvac (==0.11.2)
Requires-Dist: idna (==3.7)
Requires-Dist: importlib-metadata (==4.13.0)
Requires-Dist: itsdangerous (==2.2.0)
Requires-Dist: junos-eznc (==2.7.1)
Requires-Dist: loguru (==0.7.2)
Requires-Dist: lxml (==5.2.2)
Requires-Dist: mypy-extensions (==0.4.4)
Requires-Dist: napalm (==3.3.1)
Requires-Dist: ncclient (==0.6.15)
Requires-Dist: netaddr (==1.3.0)
Requires-Dist: netmiko (==3.4.0)
Requires-Dist: nornir (==3.2.0)
Requires-Dist: ntc_templates (==5.1.0)
Requires-Dist: numpy (==1.26.4)
Requires-Dist: openpyxl (==3.0.9)
Requires-Dist: pandas (==1.3.4)
Requires-Dist: paramiko (==3.4.0)
Requires-Dist: passlib (==1.7.4)
Requires-Dist: pycparser (==2.22)
Requires-Dist: pyeapi (==1.0.2)
Requires-Dist: pymongo (==4.7.3)
Requires-Dist: pyparsing (==3.1.2)
Requires-Dist: pyserial (==3.5)
Requires-Dist: python-dateutil (==2.9.0.post0)
Requires-Dist: pytz (==2024.1)
Requires-Dist: requests (==2.32.3)
Requires-Dist: scp (==0.15.0)
Requires-Dist: six (==1.16.0)
Requires-Dist: tabulate (==0.8.9)
Requires-Dist: tenacity (==8.4.1)
Requires-Dist: textfsm (==1.1.3)
Requires-Dist: toml (==0.10.2)
Requires-Dist: tqdm (==4.62.3)
Requires-Dist: transitions (==0.9.1)
Requires-Dist: ttp (==0.8.1)
Requires-Dist: typer (==0.4.1)
Requires-Dist: typing-extensions (==3.10.0.2)
Requires-Dist: urllib3 (==2.2.2)
Requires-Dist: win32-setctime (==1.1.0)
Requires-Dist: wrapt (==1.16.0)
Requires-Dist: yamlordereddictloader (==0.4.2)
Requires-Dist: zipp (==3.19.2)
